<stimulus name="MGSBCI" repeats="40" ex="ex_MGSBCIBlock" bgColor="0 0 0">
    <params>
        <distance>[17*16]</distance>
        <size>30</size>
        <othercolorflag>[1]</othercolorflag>
        <sizeOther>[15]</sizeOther>
        <angle>[0:45:359]</angle>
        <allAngles>[0:45:359]'</allAngles>
        <helperTargetColor>[128 128 128]'</helperTargetColor>
        <bgColor>[128 128 128]'</bgColor>
        <delayAngle>[-1]</delayAngle>
        <fixX>0</fixX>
        <fixY>0</fixY>
        <fixRad>5</fixRad>
        <fixColor>[0;0;255]</fixColor>
        <targetColor>[255 255 255]'</targetColor>
        <cursorColor>[210;128;128]</cursorColor>
        <targetColorOther>[128 128 128]'</targetColorOther>
        <annulusColor>[128 210 128]'</annulusColor>
        <timeToFix>1000</timeToFix>
        <targetDuration>200</targetDuration>
        <noFixTimeout>3000</noFixTimeout>
        <targetOnsetDelay>200</targetOnsetDelay>
        <saccadeInitiate>500</saccadeInitiate>
        <saccadeTime>150</saccadeTime>
        <stayOnTarget>100</stayOnTarget>
        <bciTargRadx>80</bciTargRadx>
        <bciTargRady>40</bciTargRady>
        <bciCursorEnable>1</bciCursorEnable>
        <bciEnable>1</bciEnable>
        <bciRewardEnable>1</bciRewardEnable>
        <cursorSize>50</cursorSize>
        <bciJuice>1</bciJuice>
        <saccadeJuice>1</saccadeJuice>
        <bciSaccadeJuice>1</bciSaccadeJuice>
        <errorBadHandshakeFlag>1</errorBadHandshakeFlag>
        <showDelayTargetFlag>1</showDelayTargetFlag>
        <lowerboundprop>0.1</lowerboundprop>
        <annulusSizeAtThresh>0.2</annulusSizeAtThresh>
        <distfunflag>1</distfunflag>
        <minRxn>0</minRxn>
        <miniblocksize>10</miniblocksize>
        <nCueTrials>1</nCueTrials>
        <noisyCursorDirNoiseFlag>0</noisyCursorDirNoiseFlag>
        <randomGain>0.1</randomGain>
        <bciinitblocklength>0</bciinitblocklength>
        <bciblocklength>1</bciblocklength>
        <shamblocklength>0</shamblocklength>
        <bciminiblocktrials>1</bciminiblocktrials>
        <shamminiblocktrials>0</shamminiblocktrials>
        <shampossible>1</shampossible>
        <recalTrial>0</recalTrial>
        <bciTrial>1</bciTrial>
        <convergeAnnulus>0</convergeAnnulus>
        <annulusvisibleflag>1</annulusvisibleflag>   
        <preBCIDelay>200</preBCIDelay>
        <postBCIDelay>0</postBCIDelay>
        <convergeDelay>0</convergeDelay>
        <noisyAnnulusFlag>0</noisyAnnulusFlag>
        <feedbackType>['a';'n';'n';'u';'l';'u';'s']</feedbackType>
        <noFixTimeoutBCI>2000</noFixTimeoutBCI>
        <detectSaccadeFlag>1</detectSaccadeFlag>
        <countMisses>1</countMisses>
        <InterTrialPause>500</InterTrialPause>
        <noisyFlatTime>1000</noisyFlatTime>
        <initSinusoidGain>0.2</initSinusoidGain>
        <noisyFreq1>5</noisyFreq1>
        <noisyFreq2>10</noisyFreq2>
        <cursorvisiblecalibflag>0</cursorvisiblecalibflag>
        <annulusvisiblecalibflag>0</annulusvisiblecalibflag>
        <autocalibflag>0</autocalibflag>
        <updatesOnTarget>2</updatesOnTarget>
        <numcalibtrials>0</numcalibtrials>
        <BCIPause>500</BCIPause>
        <allowSaccadeRewardFlag>1</allowSaccadeRewardFlag>
        <doBCIwithoutcursor>1</doBCIwithoutcursor>
        <limitCursor>0</limitCursor>
        <BCIRewardPause>250</BCIRewardPause>
        <cursorCloseColor>[210;128;128]</cursorCloseColor>
        <cursorCorrectColor>[255;0;0]</cursorCorrectColor>
        <annulusTargVisibleFlag>1</annulusTargVisibleFlag>
        <annulusTargColor>[180 180 180]'</annulusTargColor>
        <cursorRadOnAnnulus>10</cursorRadOnAnnulus>
        <annulusSize>round(2*17)</annulusSize>
        <annulusThickness>4</annulusThickness>
        <Cmax>round(2*17)</Cmax>
        <cursorRad>10</cursorRad>
        <BCIDistanceThresh>15</BCIDistanceThresh>
        <workspaceMult>[0.75]</workspaceMult>
        <fixDuration>[3400]</fixDuration> 
        <replaceSaccWinRadWithAnnulusFlag>0</replaceSaccWinRadWithAnnulusFlag>
        <replaceFixWinRadWithAnnulusFlag>0</replaceFixWinRadWithAnnulusFlag>
        <peripheralTargConditionFlag>0</peripheralTargConditionFlag>
        <numPeripheralConds>4</numPeripheralConds>
        <BCISaccadeReward>150</BCISaccadeReward>
        <countSaccades>0</countSaccades>
        <cursorVisible>[1]</cursorVisible>
        <resetMissOnCorrect>1</resetMissOnCorrect>
        <NumBlockCueTrials>2</NumBlockCueTrials>   
        <NumBlockNonCueTrials>2</NumBlockNonCueTrials>
        <maxmissesprompt>15</maxmissesprompt>
        <maxmissesabort>16</maxmissesabort>
        <perturbStartTrialNum>10120</perturbStartTrialNum>
        <perturbEndTrialNum>10600</perturbEndTrialNum>
        <washoutEndTrialNum>10601</washoutEndTrialNum>
        <perturbAngle>[0]'</perturbAngle>
        <blankCursorInFixWinFlag>0</blankCursorInFixWinFlag>
        <blankRad>1</blankRad>
        <maxmissesabortCue>3</maxmissesabortCue>
        <peripheralPerturbAngle>0</peripheralPerturbAngle>
        <randomPerturbAmount>0</randomPerturbAmount>
        <randomPerturb>[0]</randomPerturb>
        <peripheralTargVisibleDuringCue>[1]</peripheralTargVisibleDuringCue>
        <blockCueOn>[1]</blockCueOn>  
    </params>
    <randoms>
        <targetBrightness>[128 131 134 137 140 141 146 149]</targetBrightness>
        <randomDirection>[0:45:315]+22.5</randomDirection>      
    </randoms>
</stimulus>                                       
